{"sections":{"cart-items":{"type":"main-cart-items","settings":{"color_scheme":"background-1","padding_top":36,"padding_bottom":36}},"17442996802b48664a":{"type":"apps","settings":{"include_margins":true}},"1746115903c51c2e1c":{"type":"apps","settings":{"include_margins":true}},"cart-footer":{"type":"main-cart-footer","blocks":{"subtotal":{"type":"subtotal","settings":{}},"buttons":{"type":"buttons","settings":{}}},"block_order":["subtotal","buttons"],"settings":{"color_scheme":"background-1","padding_top":20,"padding_bottom":40}}},"order":["cart-items","17442996802b48664a","1746115903c51c2e1c","cart-footer"]}